pipedash/DataRegistryApiService.py
pipedash/DrawableComponent.py
pipedash/DrawableComponentData.py
pipedash/DrawableProperties.py
pipedash/PipedashWorker.py
pipedash/Registrar.py
pipedash/__init__.py
pipedash/helper.py
pipedash/index.py
pipedash-1.3.12.dist-info/METADATA
pipedash-1.3.12.dist-info/WHEEL
pipedash-1.3.12.dist-info/entry_points.txt
pipedash-1.3.12.dist-info/top_level.txt
pipedash-1.3.12.dist-info/RECORD
