Metadata-Version: 2.1
Name: pipedash
Version: 1.3.12
Summary: Develop new code for your pipedash widgets
Home-page: https://gitlab.com/pipedash/pipedash-python
Author: pipedash
Author-email: donnercody86@gmail.com
License: MIT
Platform: UNKNOWN
Classifier: License :: OSI Approved :: MIT License
Classifier: Programming Language :: Python
Classifier: Programming Language :: Python :: 2
Classifier: Programming Language :: Python :: 3
Requires-Dist: requests
Requires-Dist: semver
Requires-Dist: datascience
Requires-Dist: munch
Requires-Dist: coolname
Requires-Dist: google
Requires-Dist: pika
Requires-Dist: aio-pika
Requires-Dist: grpcio
Requires-Dist: grpcio-tools
Requires-Dist: protobuf
Requires-Dist: cython
Requires-Dist: ipython
Requires-Dist: ipykernel
Requires-Dist: pandas
Requires-Dist: websocket-client
Requires-Dist: plotly
Requires-Dist: simplejson
Requires-Dist: ipynb-path
Requires-Dist: pyarrow
Requires-Dist: python-dateutil
